acoustics_toolbox/__init__.py
acoustics_toolbox/acoustics_basics.py
acoustics_toolbox/outdoor_propagation_tools.py
acoustics_toolbox/replicate_iso9613_1.py
acoustics_toolbox/replicate_iso9613_2.py
acoustics_toolbox-0.0.6.dist-info/METADATA
acoustics_toolbox-0.0.6.dist-info/WHEEL
acoustics_toolbox-0.0.6.dist-info/RECORD
